teradata_mcp_server/__init__.py
teradata_mcp_server/__main__.py
teradata_mcp_server/app.py
teradata_mcp_server/middleware.py
teradata_mcp_server/server.py
teradata_mcp_server/utils.py
teradata_mcp_server/config/__init__.py
teradata_mcp_server/config/profiles.yml
teradata_mcp_server/config/rag_config.yml
teradata_mcp_server/config/sql_opt_config.yml
teradata_mcp_server/tools/__init__.py
teradata_mcp_server/tools/auth_cache.py
teradata_mcp_server/tools/auth_validation.py
teradata_mcp_server/tools/constants.py
teradata_mcp_server/tools/module_loader.py
teradata_mcp_server/tools/td_connect.py
teradata_mcp_server/tools/base/README.md
teradata_mcp_server/tools/base/__init__.py
teradata_mcp_server/tools/base/base_objects.yml
teradata_mcp_server/tools/base/base_resources.py
teradata_mcp_server/tools/base/base_tools.py
teradata_mcp_server/tools/dba/README.md
teradata_mcp_server/tools/dba/__init__.py
teradata_mcp_server/tools/dba/dba_objects.yml
teradata_mcp_server/tools/dba/dba_resources.py
teradata_mcp_server/tools/dba/dba_tools.py
teradata_mcp_server/tools/fs/README.md
teradata_mcp_server/tools/fs/__init__.py
teradata_mcp_server/tools/fs/fs_objects.yml
teradata_mcp_server/tools/fs/fs_prompts.py
teradata_mcp_server/tools/fs/fs_resources.py
teradata_mcp_server/tools/fs/fs_tools.py
teradata_mcp_server/tools/fs/fs_utils.py
teradata_mcp_server/tools/plot/README.md
teradata_mcp_server/tools/plot/__init__.py
teradata_mcp_server/tools/plot/plot_objects.yml
teradata_mcp_server/tools/plot/plot_prompts.py
teradata_mcp_server/tools/plot/plot_resources.py
teradata_mcp_server/tools/plot/plot_tools.py
teradata_mcp_server/tools/plot/plot_utils.py
teradata_mcp_server/tools/qlty/README.md
teradata_mcp_server/tools/qlty/__init__.py
teradata_mcp_server/tools/qlty/qlty_objects.yml
teradata_mcp_server/tools/qlty/qlty_resources.py
teradata_mcp_server/tools/qlty/qlty_tools.py
teradata_mcp_server/tools/rag/README.md
teradata_mcp_server/tools/rag/__init__.py
teradata_mcp_server-0.1.6.dist-info/METADATA
teradata_mcp_server-0.1.6.dist-info/WHEEL
teradata_mcp_server-0.1.6.dist-info/entry_points.txt
teradata_mcp_server-0.1.6.dist-info/licenses/LICENSE
teradata_mcp_server-0.1.6.dist-info/RECORD
